sebastos/__init__.py
sebastos/main.py
sebastos-0.1.1.dist-info/METADATA
sebastos-0.1.1.dist-info/WHEEL
sebastos-0.1.1.dist-info/entry_points.txt
sebastos-0.1.1.dist-info/RECORD
