Metadata-Version: 2.4
Name: sebastos
Version: 0.1.1
Summary: local query&sync of standardebooks
Requires-Python: >=3.12
Requires-Dist: requests>=2.32.5
Requires-Dist: tqdm>=4.67.1
